bitcoincli/__init__.py
bitcoincli/client.py
bitcoincli-1.0.0.dist-info/LICENSE
bitcoincli-1.0.0.dist-info/METADATA
bitcoincli-1.0.0.dist-info/WHEEL
bitcoincli-1.0.0.dist-info/top_level.txt
bitcoincli-1.0.0.dist-info/RECORD
