Metadata-Version: 2.1
Name: bitcoincli
Version: 1.0.0
Summary: A python binding for Bitcoin Json-RPC API
Home-page: https://github.com/chainstack/bitcoincli
Author: Evgeny Konstantinov, Alex Khaerov, Federico Cardoso
Author-email: evgeny.konstantinov@chainstack.com,alex.khaerov@chainstack.com,federico.cardoso@dxmarkets.com
License: BSD
Keywords: bitcoin python blockchain jsonrpc
Platform: UNKNOWN
Requires-Dist: requests (>=2.20.0)
